Workbook

Sheet Revenue Model
A1: NVIDIA Corporation — Revenue Model
A2: Segment build-up; projected on blue growth-rate inputs
A3: US$M unless noted · FY ends late Jan · per-share split-adjusted (10:1 Jun-2024) · blue=input black=formula green=link
B5: FY2023 | C5: FY2024 | D5: FY2025 | E5: FY2026 | F5: FY2027E | G5: FY2028E | H5: FY2029E | I5: FY2030E | J5: FY2031E
A6: REVENUE BY SEGMENT ($M)
A7: Data Center | B7: 15005 | C7: 47525 | D7: 115186 | E7: 193737 | F7: =E7*(1+F8) | G7: =F7*(1+G8) | H7: =G7*(1+H8) | I7: =H7*(1+I8) | J7: =I7*(1+J8)
A8: Data Center growth % | C8: =C7/B7-1 | D8: =D7/C7-1 | E8: =E7/D7-1 | F8: 0.78 | G8: 0.35 | H8: 0.22 | I8: 0.15 | J8: 0.12
A9: Gaming | B9: 9067 | C9: 10447 | D9: 11350 | E9: 16042 | F9: =E9*(1+F10) | G9: =F9*(1+G10) | H9: =G9*(1+H10) | I9: =H9*(1+I10) | J9: =I9*(1+J10)
A10: Gaming growth % | C10: =C9/B9-1 | D10: =D9/C9-1 | E10: =E9/D9-1 | F10: 0.12 | G10: 0.08 | H10: 0.06 | I10: 0.05 | J10: 0.05
A11: Professional Visualization | B11: 1544 | C11: 1553 | D11: 1878 | E11: 3191 | F11: =E11*(1+F12) | G11: =F11*(1+G12) | H11: =G11*(1+H12) | I11: =H11*(1+I12) | J11: =I11*(1+J12)
A12: Professional Visualization growth % | C12: =C11/B11-1 | D12: =D11/C11-1 | E12: =E11/D11-1 | F12: 0.15 | G12: 0.12 | H12: 0.1 | I12: 0.08 | J12: 0.07
A13: Automotive & Robotics | B13: 903 | C13: 1091 | D13: 1694 | E13: 2349 | F13: =E13*(1+F14) | G13: =F13*(1+G14) | H13: =G13*(1+H14) | I13: =H13*(1+I14) | J13: =I13*(1+J14)
A14: Automotive & Robotics growth % | C14: =C13/B13-1 | D14: =D13/C13-1 | E14: =E13/D13-1 | F14: 0.45 | G14: 0.38 | H14: 0.3 | I14: 0.25 | J14: 0.2
A15: OEM & Other | B15: 455 | C15: 306 | D15: 389 | E15: 619 | F15: =E15*(1+F16) | G15: =F15*(1+G16) | H15: =G15*(1+H16) | I15: =H15*(1+I16) | J15: =I15*(1+J16)
A16: OEM & Other growth % | C16: =C15/B15-1 | D16: =D15/C15-1 | E16: =E15/D15-1 | F16: 0.1 | G16: 0.08 | H16: 0.06 | I16: 0.05 | J16: 0.05
A17: TOTAL REVENUE | B17: =B7+B9+B11+B13+B15 | C17: =C7+C9+C11+C13+C15 | D17: =D7+D9+D11+D13+D15 | E17: =E7+E9+E11+E13+E15 | F17: =F7+F9+F11+F13+F15 | G17: =G7+G9+G11+G13+G15 | H17: =H7+H9+H11+H13+H15 | I17: =I7+I9+I11+I13+I15 | J17: =J7+J9+J11+J13+J15
A18: Total revenue growth % | C18: =IF(B17=0,"",C17/B17-1) | D18: =IF(C17=0,"",D17/C17-1) | E18: =IF(D17=0,"",E17/D17-1) | F18: =IF(E17=0,"",F17/E17-1) | G18: =IF(F17=0,"",G17/F17-1) | H18: =IF(G17=0,"",H17/G17-1) | I18: =IF(H17=0,"",I17/H17-1) | J18: =IF(I17=0,"",J17/I17-1)
A20: SEGMENT MIX (% of total)
A21: Data Center | B21: =IF(B17=0,"",B7/B17) | C21: =IF(C17=0,"",C7/C17) | D21: =IF(D17=0,"",D7/D17) | E21: =IF(E17=0,"",E7/E17) | F21: =IF(F17=0,"",F7/F17) | G21: =IF(G17=0,"",G7/G17) | H21: =IF(H17=0,"",H7/H17) | I21: =IF(I17=0,"",I7/I17) | J21: =IF(J17=0,"",J7/J17)
A22: Gaming | B22: =IF(B17=0,"",B9/B17) | C22: =IF(C17=0,"",C9/C17) | D22: =IF(D17=0,"",D9/D17) | E22: =IF(E17=0,"",E9/E17) | F22: =IF(F17=0,"",F9/F17) | G22: =IF(G17=0,"",G9/G17) | H22: =IF(H17=0,"",H9/H17) | I22: =IF(I17=0,"",I9/I17) | J22: =IF(J17=0,"",J9/J17)
A23: Professional Visualization | B23: =IF(B17=0,"",B11/B17) | C23: =IF(C17=0,"",C11/C17) | D23: =IF(D17=0,"",D11/D17) | E23: =IF(E17=0,"",E11/E17) | F23: =IF(F17=0,"",F11/F17) | G23: =IF(G17=0,"",G11/G17) | H23: =IF(H17=0,"",H11/H17) | I23: =IF(I17=0,"",I11/I17) | J23: =IF(J17=0,"",J11/J17)
A24: Automotive & Robotics | B24: =IF(B17=0,"",B13/B17) | C24: =IF(C17=0,"",C13/C17) | D24: =IF(D17=0,"",D13/D17) | E24: =IF(E17=0,"",E13/E17) | F24: =IF(F17=0,"",F13/F17) | G24: =IF(G17=0,"",G13/G17) | H24: =IF(H17=0,"",H13/H17) | I24: =IF(I17=0,"",I13/I17) | J24: =IF(J17=0,"",J13/J17)
A25: OEM & Other | B25: =IF(B17=0,"",B15/B17) | C25: =IF(C17=0,"",C15/C17) | D25: =IF(D17=0,"",D15/D17) | E25: =IF(E17=0,"",E15/E17) | F25: =IF(F17=0,"",F15/F17) | G25: =IF(G17=0,"",G15/G17) | H25: =IF(H17=0,"",H15/H17) | I25: =IF(I17=0,"",I15/I17) | J25: =IF(J17=0,"",J15/J17)
A27: REVENUE BY GEOGRAPHY (billed-to; % × total, estimated from 10-K)
A28: United States % | B28: 0.28 | C28: 0.35 | D28: 0.47 | E28: 0.52 | F28: 0.53 | G28: 0.54 | H28: 0.55 | I28: 0.55 | J28: 0.55
A29: Taiwan % | B29: 0.24 | C29: 0.22 | D29: 0.16 | E29: 0.14 | F29: 0.14 | G29: 0.13 | H29: 0.13 | I29: 0.13 | J29: 0.13
A30: China (incl. HK) % | B30: 0.26 | C30: 0.22 | D30: 0.13 | E30: 0.05 | F30: 0.04 | G30: 0.04 | H30: 0.04 | I30: 0.04 | J30: 0.04
A31: Other Asia-Pacific % | B31: 0.14 | C31: 0.13 | D31: 0.16 | E31: 0.19 | F31: 0.19 | G31: 0.19 | H31: 0.18 | I31: 0.18 | J31: 0.18
A32: Europe / EMEA % | B32: 0.06 | C32: 0.06 | D32: 0.06 | E32: 0.08 | F32: 0.08 | G32: 0.08 | H32: 0.08 | I32: 0.08 | J32: 0.08
A33: Rest of World % | B33: 0.02 | C33: 0.02 | D33: 0.02 | E33: 0.02 | F33: 0.02 | G33: 0.02 | H33: 0.02 | I33: 0.02 | J33: 0.02
A34: United States ($M) | B34: =B28*B17 | C34: =C28*C17 | D34: =D28*D17 | E34: =E28*E17 | F34: =F28*F17 | G34: =G28*G17 | H34: =H28*H17 | I34: =I28*I17 | J34: =J28*J17
A35: Taiwan ($M) | B35: =B29*B17 | C35: =C29*C17 | D35: =D29*D17 | E35: =E29*E17 | F35: =F29*F17 | G35: =G29*G17 | H35: =H29*H17 | I35: =I29*I17 | J35: =J29*J17
A36: China (incl. HK) ($M) | B36: =B30*B17 | C36: =C30*C17 | D36: =D30*D17 | E36: =E30*E17 | F36: =F30*F17 | G36: =G30*G17 | H36: =H30*H17 | I36: =I30*I17 | J36: =J30*J17
A37: Other Asia-Pacific ($M) | B37: =B31*B17 | C37: =C31*C17 | D37: =D31*D17 | E37: =E31*E17 | F37: =F31*F17 | G37: =G31*G17 | H37: =H31*H17 | I37: =I31*I17 | J37: =J31*J17
A38: Europe / EMEA ($M) | B38: =B32*B17 | C38: =C32*C17 | D38: =D32*D17 | E38: =E32*E17 | F38: =F32*F17 | G38: =G32*G17 | H38: =H32*H17 | I38: =I32*I17 | J38: =J32*J17
A39: Rest of World ($M) | B39: =B33*B17 | C39: =C33*C17 | D39: =D33*D17 | E39: =E33*E17 | F39: =F33*F17 | G39: =G33*G17 | H39: =H33*H17 | I39: =I33*I17 | J39: =J33*J17
A40: Geography check (≈0) | B40: =SUM(B34:B39)-B17 | C40: =SUM(C34:C39)-C17 | D40: =SUM(D34:D39)-D17 | E40: =SUM(E34:E39)-E17 | F40: =SUM(F34:F39)-F17 | G40: =SUM(G34:G39)-G17 | H40: =SUM(H34:H39)-H17 | I40: =SUM(I34:I39)-I17 | J40: =SUM(J34:J39)-J17

Sheet Income Statement
A1: NVIDIA Corporation — Income Statement
A2: Actuals (blue) + margin-driven projections; revenue linked from Revenue Model
A3: US$M unless noted · FY ends late Jan · per-share split-adjusted (10:1 Jun-2024) · blue=input black=formula green=link
B5: FY2023 | C5: FY2024 | D5: FY2025 | E5: FY2026 | F5: FY2027E | G5: FY2028E | H5: FY2029E | I5: FY2030E | J5: FY2031E
A6: INCOME STATEMENT ($M)
A7: Total revenue | B7: ='Revenue Model'!B17 | C7: ='Revenue Model'!C17 | D7: ='Revenue Model'!D17 | E7: ='Revenue Model'!E17 | F7: ='Revenue Model'!F17 | G7: ='Revenue Model'!G17 | H7: ='Revenue Model'!H17 | I7: ='Revenue Model'!I17 | J7: ='Revenue Model'!J17
A8: Revenue growth % | C8: =IF(B7=0,"",C7/B7-1) | D8: =IF(C7=0,"",D7/C7-1) | E8: =IF(D7=0,"",E7/D7-1) | F8: =IF(E7=0,"",F7/E7-1) | G8: =IF(F7=0,"",G7/F7-1) | H8: =IF(G7=0,"",H7/G7-1) | I8: =IF(H7=0,"",I7/H7-1) | J8: =IF(I7=0,"",J7/I7-1)
A9: Gross margin % (assump) | B9: 0.5693 | C9: 0.7272 | D9: 0.7499 | E9: 0.7107 | F9: 0.735 | G9: 0.735 | H9: 0.73 | I9: 0.725 | J9: 0.72
A10: Cost of revenue | B10: =B7*(1-B9) | C10: =C7*(1-C9) | D10: =D7*(1-D9) | E10: =E7*(1-E9) | F10: =F7*(1-F9) | G10: =G7*(1-G9) | H10: =H7*(1-H9) | I10: =I7*(1-I9) | J10: =J7*(1-J9)
A11: Gross profit | B11: =B7-B10 | C11: =C7-C10 | D11: =D7-D10 | E11: =E7-E10 | F11: =F7-F10 | G11: =G7-G10 | H11: =H7-H10 | I11: =I7-I10 | J11: =J7-J10
A12: OPERATING EXPENSES ($M)
A13: R&D % of rev (assump) | B13: 0.2721 | C13: 0.1424 | D13: 0.099 | E13: 0.0857 | F13: 0.115 | G13: 0.12 | H13: 0.125 | I13: 0.13 | J13: 0.13
A14: Research & development | B14: =B7*B13 | C14: =C7*C13 | D14: =D7*D13 | E14: =E7*E13 | F14: =F7*F13 | G14: =G7*G13 | H14: =H7*H13 | I14: =I7*I13 | J14: =J7*J13
A15: SG&A % of rev (assump) | B15: 0.0905 | C15: 0.0436 | D15: 0.0268 | E15: 0.0212 | F15: 0.03 | G15: 0.032 | H15: 0.034 | I15: 0.035 | J15: 0.035
A16: Selling, general & admin | B16: =B7*B15 | C16: =C7*C15 | D16: =D7*D15 | E16: =E7*E15 | F16: =F7*F15 | G16: =G7*G15 | H16: =H7*H15 | I16: =I7*I15 | J16: =J7*J15
A17: Total operating expenses | B17: =B14+B16 | C17: =C14+C16 | D17: =D14+D16 | E17: =E14+E16 | F17: =F14+F16 | G17: =G14+G16 | H17: =H14+H16 | I17: =I14+I16 | J17: =J14+J16
A18: Other operating items (net) | B18: 1353 | C18: 0 | D18: 0 | E18: 0 | F18: 0 | G18: 0 | H18: 0 | I18: 0 | J18: 0
A19: Operating income (EBIT) | B19: =B11-B17-B18 | C19: =C11-C17-C18 | D19: =D11-D17-D18 | E19: =E11-E17-E18 | F19: =F11-F17-F18 | G19: =G11-G17-G18 | H19: =H11-H17-H18 | I19: =I11-I17-I18 | J19: =J11-J17-J18
A20: EBIT margin % | B20: =IF(B7=0,"",B19/B7) | C20: =IF(C7=0,"",C19/C7) | D20: =IF(D7=0,"",D19/D7) | E20: =IF(E7=0,"",E19/E7) | F20: =IF(F7=0,"",F19/F7) | G20: =IF(G7=0,"",G19/G7) | H20: =IF(H7=0,"",H19/H7) | I20: =IF(I7=0,"",I19/I7) | J20: =IF(J7=0,"",J19/J7)
A21: Depreciation & amortization | B21: 1544 | C21: 1508 | D21: 1864 | E21: 2843 | F21: =F7*0.02 | G21: =G7*0.022 | H21: =H7*0.024 | I21: =I7*0.025 | J21: =J7*0.025
A22: EBITDA | B22: =B19+B21 | C22: =C19+C21 | D22: =D19+D21 | E22: =E19+E21 | F22: =F19+F21 | G22: =G19+G21 | H22: =H19+H21 | I22: =I19+I21 | J22: =J19+J21
A23: EBITDA margin % | B23: =IF(B7=0,"",B22/B7) | C23: =IF(C7=0,"",C22/C7) | D23: =IF(D7=0,"",D22/D7) | E23: =IF(E7=0,"",E22/E7) | F23: =IF(F7=0,"",F22/F7) | G23: =IF(G7=0,"",G22/G7) | H23: =IF(H7=0,"",H22/H7) | I23: =IF(I7=0,"",I22/I7) | J23: =IF(J7=0,"",J22/J7)
A24: NON-OPERATING & TAXES ($M)
A25: Net interest & other (norm.) | B25: -43 | C25: 846 | D25: 2573 | E25: 11063 | F25: 2300 | G25: 2500 | H25: 2700 | I25: 2900 | J25: 3100
A26: Pre-tax income | B26: =B19+B25 | C26: =C19+C25 | D26: =D19+D25 | E26: =E19+E25 | F26: =F19+F25 | G26: =G19+G25 | H26: =H19+H25 | I26: =I19+I25 | J26: =J19+J25
A27: Tax rate % (assump) | B27: -0.0447 | C27: 0.12 | D27: 0.1326 | E27: 0.1512 | F27: 0.16 | G27: 0.16 | H27: 0.16 | I27: 0.16 | J27: 0.16
A28: Income tax expense | B28: =B26*B27 | C28: =C26*C27 | D28: =D26*D27 | E28: =E26*E27 | F28: =F26*F27 | G28: =G26*G27 | H28: =H26*H27 | I28: =I26*I27 | J28: =J26*J27
A29: NET INCOME | B29: =B26-B28 | C29: =C26-C28 | D29: =D26-D28 | E29: =E26-E28 | F29: =F26-F28 | G29: =G26-G28 | H29: =H26-H28 | I29: =I26-I28 | J29: =J26-J28
A30: Net margin % | B30: =IF(B7=0,"",B29/B7) | C30: =IF(C7=0,"",C29/C7) | D30: =IF(D7=0,"",D29/D7) | E30: =IF(E7=0,"",E29/E7) | F30: =IF(F7=0,"",F29/F7) | G30: =IF(G7=0,"",G29/G7) | H30: =IF(H7=0,"",H29/H7) | I30: =IF(I7=0,"",I29/I7) | J30: =IF(J7=0,"",J29/J7)
A31: PER SHARE (split-adjusted)
A32: Diluted shares (M) | B32: 25070 | C32: 24940 | D32: 24804 | E32: 24514 | F32: =E32*(1-0.012) | G32: =F32*(1-0.012) | H32: =G32*(1-0.012) | I32: =H32*(1-0.012) | J32: =I32*(1-0.012)
A33: Diluted EPS | B33: =B29/B32 | C33: =C29/C32 | D33: =D29/D32 | E33: =E29/E32 | F33: =F29/F32 | G33: =G29/G32 | H33: =H29/H32 | I33: =I29/I32 | J33: =J29/J32

Sheet Cash Flow
A1: NVIDIA Corporation — Cash Flow Statement
A2: ΔWC linked from Balance Sheet so cash ties out; FCF feeds DCF
A3: US$M unless noted · FY ends late Jan · per-share split-adjusted (10:1 Jun-2024) · blue=input black=formula green=link
B5: FY2023 | C5: FY2024 | D5: FY2025 | E5: FY2026 | F5: FY2027E | G5: FY2028E | H5: FY2029E | I5: FY2030E | J5: FY2031E
A6: OPERATING ACTIVITIES ($M)
A7: Net income | B7: ='Income Statement'!B29 | C7: ='Income Statement'!C29 | D7: ='Income Statement'!D29 | E7: ='Income Statement'!E29 | F7: ='Income Statement'!F29 | G7: ='Income Statement'!G29 | H7: ='Income Statement'!H29 | I7: ='Income Statement'!I29 | J7: ='Income Statement'!J29
A8: Depreciation & amortization | B8: ='Income Statement'!B21 | C8: ='Income Statement'!C21 | D8: ='Income Statement'!D21 | E8: ='Income Statement'!E21 | F8: ='Income Statement'!F21 | G8: ='Income Statement'!G21 | H8: ='Income Statement'!H21 | I8: ='Income Statement'!I21 | J8: ='Income Statement'!J21
A9: Stock-based compensation | B9: 2709 | C9: 3549 | D9: 4737 | E9: 6386 | F9: ='Income Statement'!F7*0.04 | G9: ='Income Statement'!G7*0.04 | H9: ='Income Statement'!H7*0.04 | I9: ='Income Statement'!I7*0.04 | J9: ='Income Statement'!J7*0.04
A10: Change in working capital | B10: -1622 | C10: -3743 | D10: -10228 | E10: -17348 | F10: =-(('Balance Sheet'!F8-'Balance Sheet'!E8)+('Balance Sheet'!F9-'Balance Sheet'!E9)+('Balance Sheet'!F10-'Balance Sheet'!E10))+(('Balance Sheet'!F17-'Balance Sheet'!E17)+('Balance Sheet'!F18-'Balance Sheet'!E18)) | G10: =-(('Balance Sheet'!G8-'Balance Sheet'!F8)+('Balance Sheet'!G9-'Balance Sheet'!F9)+('Balance Sheet'!G10-'Balance Sheet'!F10))+(('Balance Sheet'!G17-'Balance Sheet'!F17)+('Balance Sheet'!G18-'Balance Sheet'!F18)) | H10: =-(('Balance Sheet'!H8-'Balance Sheet'!G8)+('Balance Sheet'!H9-'Balance Sheet'!G9)+('Balance Sheet'!H10-'Balance Sheet'!G10))+(('Balance Sheet'!H17-'Balance Sheet'!G17)+('Balance Sheet'!H18-'Balance Sheet'!G18)) | I10: =-(('Balance Sheet'!I8-'Balance Sheet'!H8)+('Balance Sheet'!I9-'Balance Sheet'!H9)+('Balance Sheet'!I10-'Balance Sheet'!H10))+(('Balance Sheet'!I17-'Balance Sheet'!H17)+('Balance Sheet'!I18-'Balance Sheet'!H18)) | J10: =-(('Balance Sheet'!J8-'Balance Sheet'!I8)+('Balance Sheet'!J9-'Balance Sheet'!I9)+('Balance Sheet'!J10-'Balance Sheet'!I10))+(('Balance Sheet'!J17-'Balance Sheet'!I17)+('Balance Sheet'!J18-'Balance Sheet'!I18))
A11: Deferred tax & other non-cash | B11: -1358 | C11: -2984 | D11: -5164 | E11: -9230 | F11: 0 | G11: 0 | H11: 0 | I11: 0 | J11: 0
A12: Cash from operations | B12: =B7+B8+B9+B10+B11 | C12: =C7+C8+C9+C10+C11 | D12: =D7+D8+D9+D10+D11 | E12: =E7+E8+E9+E10+E11 | F12: =F7+F8+F9+F10+F11 | G12: =G7+G8+G9+G10+G11 | H12: =H7+H8+H9+H10+H11 | I12: =I7+I8+I9+I10+I11 | J12: =J7+J8+J9+J10+J11
A13: INVESTING ACTIVITIES ($M)
A14: Capital expenditures | B14: -1833 | C14: -1069 | D14: -3236 | E14: -6042 | F14: =-'Income Statement'!F7*0.035 | G14: =-'Income Statement'!G7*0.035 | H14: =-'Income Statement'!H7*0.033 | I14: =-'Income Statement'!I7*0.03 | J14: =-'Income Statement'!J7*0.03
A15: FREE CASH FLOW | B15: =B12+B14 | C15: =C12+C14 | D15: =D12+D14 | E15: =E12+E14 | F15: =F12+F14 | G15: =G12+G14 | H15: =H12+H14 | I15: =I12+I14 | J15: =J12+J14
A16: FCF margin % | B16: =IF('Income Statement'!B7=0,"",B15/'Income Statement'!B7) | C16: =IF('Income Statement'!C7=0,"",C15/'Income Statement'!C7) | D16: =IF('Income Statement'!D7=0,"",D15/'Income Statement'!D7) | E16: =IF('Income Statement'!E7=0,"",E15/'Income Statement'!E7) | F16: =IF('Income Statement'!F7=0,"",F15/'Income Statement'!F7) | G16: =IF('Income Statement'!G7=0,"",G15/'Income Statement'!G7) | H16: =IF('Income Statement'!H7=0,"",H15/'Income Statement'!H7) | I16: =IF('Income Statement'!I7=0,"",I15/'Income Statement'!I7) | J16: =IF('Income Statement'!J7=0,"",J15/'Income Statement'!J7)
A17: FINANCING ACTIVITIES ($M) — historical only
A18: Dividends paid | B18: -398 | C18: -395 | D18: -834 | E18: -974
A19: Share repurchases | B19: -10039 | C19: -9533 | D19: -33706 | E19: -40086

Sheet Balance Sheet
A1: NVIDIA Corporation — Balance Sheet
A2: Actuals (blue); projections roll WC off revenue, PP&E off CapEx−D&A, equity off net income
A3: US$M unless noted · FY ends late Jan · per-share split-adjusted (10:1 Jun-2024) · blue=input black=formula green=link
B5: FY2023 | C5: FY2024 | D5: FY2025 | E5: FY2026 | F5: FY2027E | G5: FY2028E | H5: FY2029E | I5: FY2030E | J5: FY2031E
A6: ASSETS ($M)
A7: Cash & investments | B7: 13296 | C7: 25984 | D7: 43210 | E7: 62556 | F7: =E7+'Cash Flow'!F12+'Cash Flow'!F14 | G7: =F7+'Cash Flow'!G12+'Cash Flow'!G14 | H7: =G7+'Cash Flow'!H12+'Cash Flow'!H14 | I7: =H7+'Cash Flow'!I12+'Cash Flow'!I14 | J7: =I7+'Cash Flow'!J12+'Cash Flow'!J14
A8: Accounts receivable | B8: 3827 | C8: 9999 | D8: 23065 | E8: 38466 | F8: ='Income Statement'!F7*0.1781 | G8: ='Income Statement'!G7*0.1781 | H8: ='Income Statement'!H7*0.1781 | I8: ='Income Statement'!I7*0.1781 | J8: ='Income Statement'!J7*0.1781
A9: Inventory | B9: 5159 | C9: 5282 | D9: 10080 | E9: 21403 | F9: ='Income Statement'!F7*0.0991 | G9: ='Income Statement'!G7*0.0991 | H9: ='Income Statement'!H7*0.0991 | I9: ='Income Statement'!I7*0.0991 | J9: ='Income Statement'!J7*0.0991
A10: Other current assets | B10: 791 | C10: 3080 | D10: 3771 | E10: 3180 | F10: ='Income Statement'!F7*0.0147 | G10: ='Income Statement'!G7*0.0147 | H10: ='Income Statement'!H7*0.0147 | I10: ='Income Statement'!I7*0.0147 | J10: ='Income Statement'!J7*0.0147
A11: Total current assets | B11: =SUM(B7:B10) | C11: =SUM(C7:C10) | D11: =SUM(D7:D10) | E11: =SUM(E7:E10) | F11: =SUM(F7:F10) | G11: =SUM(G7:G10) | H11: =SUM(H7:H10) | I11: =SUM(I7:I10) | J11: =SUM(J7:J10)
A12: PP&E, net | B12: 4845 | C12: 5260 | D12: 8076 | E12: 13250 | F12: =E12+'Income Statement'!F7*0.035-'Income Statement'!F21 | G12: =F12+'Income Statement'!G7*0.035-'Income Statement'!G21 | H12: =G12+'Income Statement'!H7*0.033-'Income Statement'!H21 | I12: =H12+'Income Statement'!I7*0.03-'Income Statement'!I21 | J12: =I12+'Income Statement'!J7*0.03-'Income Statement'!J21
A13: Goodwill & intangibles | B13: 6048 | C13: 5542 | D13: 5995 | E13: 24138 | F13: 24138 | G13: 24138 | H13: 24138 | I13: 24138 | J13: 24138
A14: Other non-current assets | B14: 7216 | C14: 10581 | D14: 17404 | E14: 43810 | F14: 43810 | G14: 43810 | H14: 43810 | I14: 43810 | J14: 43810
A15: TOTAL ASSETS | B15: =B11+B12+B13+B14 | C15: =C11+C12+C13+C14 | D15: =D11+D12+D13+D14 | E15: =E11+E12+E13+E14 | F15: =F11+F12+F13+F14 | G15: =G11+G12+G13+G14 | H15: =H11+H12+H13+H14 | I15: =I11+I12+I13+I14 | J15: =J11+J12+J13+J14
A16: LIABILITIES & EQUITY ($M)
A17: Accounts payable | B17: 1193 | C17: 2699 | D17: 6310 | E17: 9812 | F17: ='Income Statement'!F7*0.0454 | G17: ='Income Statement'!G7*0.0454 | H17: ='Income Statement'!H7*0.0454 | I17: ='Income Statement'!I7*0.0454 | J17: ='Income Statement'!J7*0.0454
A18: Accrued & other current | B18: 4120 | C18: 6682 | D18: 11737 | E18: 21352 | F18: ='Income Statement'!F7*0.0989 | G18: ='Income Statement'!G7*0.0989 | H18: ='Income Statement'!H7*0.0989 | I18: ='Income Statement'!I7*0.0989 | J18: ='Income Statement'!J7*0.0989
A19: Short-term debt | B19: 1250 | C19: 1250 | D19: 0 | E19: 999 | F19: 999 | G19: 999 | H19: 999 | I19: 999 | J19: 999
A20: Total current liabilities | B20: =B17+B18+B19 | C20: =C17+C18+C19 | D20: =D17+D18+D19 | E20: =E17+E18+E19 | F20: =F17+F18+F19 | G20: =G17+G18+G19 | H20: =H17+H18+H19 | I20: =I17+I18+I19 | J20: =J17+J18+J19
A21: Long-term debt | B21: 9703 | C21: 8459 | D21: 8463 | E21: 7469 | F21: 7469 | G21: 7469 | H21: 7469 | I21: 7469 | J21: 7469
A22: Other non-current liabilities | B22: 2815 | C22: 3660 | D22: 5764 | E22: 9878 | F22: 9878 | G22: 9878 | H22: 9878 | I22: 9878 | J22: 9878
A23: TOTAL LIABILITIES | B23: =B20+B21+B22 | C23: =C20+C21+C22 | D23: =D20+D21+D22 | E23: =E20+E21+E22 | F23: =F20+F21+F22 | G23: =G20+G21+G22 | H23: =H20+H21+H22 | I23: =I20+I21+I22 | J23: =J20+J21+J22
A24: TOTAL EQUITY | B24: 22101 | C24: 42978 | D24: 79327 | E24: 157293 | F24: =E24+'Income Statement'!F29+'Income Statement'!F7*0.04 | G24: =F24+'Income Statement'!G29+'Income Statement'!G7*0.04 | H24: =G24+'Income Statement'!H29+'Income Statement'!H7*0.04 | I24: =H24+'Income Statement'!I29+'Income Statement'!I7*0.04 | J24: =I24+'Income Statement'!J29+'Income Statement'!J7*0.04
A25: TOTAL LIAB + EQUITY | B25: =B23+B24 | C25: =C23+C24 | D25: =D23+D24 | E25: =E23+E24 | F25: =F23+F24 | G25: =G23+G24 | H25: =H23+H24 | I25: =I23+I24 | J25: =J23+J24
A26: Balance check (A−L−E) | B26: =B15-B25 | C26: =C15-C25 | D26: =D15-D25 | E26: =E15-E25 | F26: =F15-F25 | G26: =G15-G25 | H26: =H15-H25 | I26: =I15-I25 | J26: =J15-J25

Sheet Scenarios
A1: NVIDIA Corporation — Scenario Analysis
A2: Five-year outlook to FY2031E. Base = live model links; Bull/Bear = blue sensitivity inputs
B4: Bull | C4: Base | D4: Bear
A5: ASSUMPTIONS
A6: 5-yr revenue CAGR (FY26→31) | B6: 0.32 | C6: =('Revenue Model'!J17/'Revenue Model'!E17)^(1/5)-1 | D6: 0.16
A7: FY2031E EBITDA margin | B7: 0.6 | C7: ='Income Statement'!J22/'Income Statement'!J7 | D7: 0.52
A8: FY2031E net margin | B8: 0.5 | C8: ='Income Statement'!J29/'Income Statement'!J7 | D8: 0.4
A9: FY2031E FCF margin | B9: 0.52 | C9: ='Cash Flow'!J15/'Income Statement'!J7 | D9: 0.42
A11: REVENUE PATH ($M)
A12: FY2026 revenue (base) | B12: ='Revenue Model'!E17 | C12: ='Revenue Model'!E17 | D12: ='Revenue Model'!E17
A13: FY2027E revenue | B13: =B12*(1+B6) | C13: ='Revenue Model'!F17 | D13: =D12*(1+D6)
A14: FY2028E revenue | B14: =B13*(1+B6) | C14: ='Revenue Model'!G17 | D14: =D13*(1+D6)
A15: FY2029E revenue | B15: =B14*(1+B6) | C15: ='Revenue Model'!H17 | D15: =D14*(1+D6)
A16: FY2030E revenue | B16: =B15*(1+B6) | C16: ='Revenue Model'!I17 | D16: =D15*(1+D6)
A17: FY2031E revenue | B17: =B16*(1+B6) | C17: ='Revenue Model'!J17 | D17: =D16*(1+D6)
A19: FY2031E OUTPUTS
A20: Revenue | B20: =B17 | C20: =C17 | D20: =D17
A21: EBITDA | B21: =B17*B7 | C21: ='Income Statement'!J22 | D21: =D17*D7
A22: Net income | B22: =B17*B8 | C22: ='Income Statement'!J29 | D22: =D17*D8
A23: Diluted EPS | B23: =B22/'Income Statement'!J32 | C23: ='Income Statement'!J33 | D23: =D22/'Income Statement'!J32
A24: Free cash flow | B24: =B17*B9 | C24: ='Cash Flow'!J15 | D24: =D17*D9
A25: Cumulative FCF FY27-31 | B25: =(B13+B14+B15+B16+B17)*B9 | C25: =SUM('Cash Flow'!F15:'Cash Flow'!J15) | D25: =(D13+D14+D15+D16+D17)*D9
A27: Bull: AI capex durable, share held, GM ~72-74%. Base: guided deceleration, GM ~72%. Bear: capex digestion + ASIC share loss, GM slips to ~68-70%.

Sheet DCF Inputs
A1: NVIDIA Corporation — DCF Inputs
A2: Unlevered FCF = NOPAT + D&A − CapEx + ΔWC; WACC block are blue inputs for Task 3
A3: US$M unless noted · FY ends late Jan · per-share split-adjusted (10:1 Jun-2024) · blue=input black=formula green=link
B5: FY2023 | C5: FY2024 | D5: FY2025 | E5: FY2026 | F5: FY2027E | G5: FY2028E | H5: FY2029E | I5: FY2030E | J5: FY2031E
A6: UNLEVERED FREE CASH FLOW ($M)
A7: EBIT | B7: ='Income Statement'!B19 | C7: ='Income Statement'!C19 | D7: ='Income Statement'!D19 | E7: ='Income Statement'!E19 | F7: ='Income Statement'!F19 | G7: ='Income Statement'!G19 | H7: ='Income Statement'!H19 | I7: ='Income Statement'!I19 | J7: ='Income Statement'!J19
A8: Tax rate % | B8: ='Income Statement'!B27 | C8: ='Income Statement'!C27 | D8: ='Income Statement'!D27 | E8: ='Income Statement'!E27 | F8: ='Income Statement'!F27 | G8: ='Income Statement'!G27 | H8: ='Income Statement'!H27 | I8: ='Income Statement'!I27 | J8: ='Income Statement'!J27
A9: NOPAT | B9: =B7*(1-B8) | C9: =C7*(1-C8) | D9: =D7*(1-D8) | E9: =E7*(1-E8) | F9: =F7*(1-F8) | G9: =G7*(1-G8) | H9: =H7*(1-H8) | I9: =I7*(1-I8) | J9: =J7*(1-J8)
A10: Add: D&A | B10: ='Cash Flow'!B8 | C10: ='Cash Flow'!C8 | D10: ='Cash Flow'!D8 | E10: ='Cash Flow'!E8 | F10: ='Cash Flow'!F8 | G10: ='Cash Flow'!G8 | H10: ='Cash Flow'!H8 | I10: ='Cash Flow'!I8 | J10: ='Cash Flow'!J8
A11: Add: CapEx (neg) | B11: ='Cash Flow'!B14 | C11: ='Cash Flow'!C14 | D11: ='Cash Flow'!D14 | E11: ='Cash Flow'!E14 | F11: ='Cash Flow'!F14 | G11: ='Cash Flow'!G14 | H11: ='Cash Flow'!H14 | I11: ='Cash Flow'!I14 | J11: ='Cash Flow'!J14
A12: Add: Δ working capital | B12: ='Cash Flow'!B10 | C12: ='Cash Flow'!C10 | D12: ='Cash Flow'!D10 | E12: ='Cash Flow'!E10 | F12: ='Cash Flow'!F10 | G12: ='Cash Flow'!G10 | H12: ='Cash Flow'!H10 | I12: ='Cash Flow'!I10 | J12: ='Cash Flow'!J10
A13: UNLEVERED FCF | B13: =B9+B10+B11+B12 | C13: =C9+C10+C11+C12 | D13: =D9+D10+D11+D12 | E13: =E9+E10+E11+E12 | F13: =F9+F10+F11+F12 | G13: =G9+G10+G11+G12 | H13: =H9+H10+H11+H12 | I13: =I9+I10+I11+I12 | J13: =J9+J10+J11+J12
A15: VALUATION ASSUMPTIONS (Task 3 inputs — blue)
A16: Risk-free rate | B16: 0.043
A17: Equity risk premium | B17: 0.05
A18: Beta | B18: 1.35
A19: Cost of equity | B19: =B16+B18*B17
A20: After-tax cost of debt | B20: 0.03
A21: Equity weight | B21: 0.98
A22: Debt weight | B22: 0.02
A23: WACC | B23: =B19*B21+B20*B22
A24: Terminal growth rate | B24: 0.035
A25: Diluted shares (M, FY2026) | B25: 24514
A26: Net cash (FY2026, $M) | B26: 54088
A27: Current price ($) | B27: 207.4
A29: UFCF row (for Task 3 DCF): row 13 on this tab; terminal year = FY2031E

Sheet DCF
A1: NVIDIA — DCF
A2: Discounted cash flow — links to DCF Inputs; base case
A4: Unlevered FCF ($M) | B4: FY2027E | C4: FY2028E | D4: FY2029E | E4: FY2030E | F4: FY2031E
A5: Unlevered FCF | B5: ='DCF Inputs'!F13 | C5: ='DCF Inputs'!G13 | D5: ='DCF Inputs'!H13 | E5: ='DCF Inputs'!I13 | F5: ='DCF Inputs'!J13
A6: Discount period (t) | B6: 1 | C6: 2 | D6: 3 | E6: 4 | F6: 5
A7: Discount factor | B7: =1/(1+'DCF Inputs'!$B$23)^B6 | C7: =1/(1+'DCF Inputs'!$B$23)^C6 | D7: =1/(1+'DCF Inputs'!$B$23)^D6 | E7: =1/(1+'DCF Inputs'!$B$23)^E6 | F7: =1/(1+'DCF Inputs'!$B$23)^F6
A8: PV of FCF | B8: =B5*B7 | C8: =C5*C7 | D8: =D5*D7 | E8: =E5*E7 | F8: =F5*F7
A10: Sum PV of FCF (5yr) | B10: =SUM(B8:F8)
A11: Terminal growth (g) | B11: ='DCF Inputs'!B24
A12: WACC | B12: ='DCF Inputs'!B23
A13: Terminal value (Gordon) | B13: =F5*(1+B11)/(B12-B11)
A14: PV of terminal value | B14: =B13*F7
A15: Enterprise value | B15: =B10+B14
A16: (+) Net cash | B16: ='DCF Inputs'!B26
A17: Equity value | B17: =B15+B16
A18: Diluted shares (M) | B18: ='DCF Inputs'!B25
A19: Value per share ($) | B19: =B17/B18
A20: Current price ($) | B20: ='DCF Inputs'!B27
A21: Upside / (downside) | B21: =B19/B20-1
A22: TV as % of EV (sanity) | B22: =B14/B15

Sheet DCF Sensitivity
A1: NVIDIA — DCF Sensitivity
A2: Value per share ($): WACC (rows) × terminal growth (cols). Base case shaded
A4: WACC \ g | B4: 0.025 | C4: 0.03 | D4: 0.035 | E4: 0.04 | F4: 0.045
A5: 0.085 | B5: =('DCF'!$B$5/(1+$A5)^1+'DCF'!$C$5/(1+$A5)^2+'DCF'!$D$5/(1+$A5)^3+'DCF'!$E$5/(1+$A5)^4+'DCF'!$F$5/(1+$A5)^5+('DCF'!$F$5*(1+B$4)/($A5-B$4))/(1+$A5)^5+'DCF Inputs'!$B$26)/'DCF Inputs'!$B$25 | C5: =('DCF'!$B$5/(1+$A5)^1+'DCF'!$C$5/(1+$A5)^2+'DCF'!$D$5/(1+$A5)^3+'DCF'!$E$5/(1+$A5)^4+'DCF'!$F$5/(1+$A5)^5+('DCF'!$F$5*(1+C$4)/($A5-C$4))/(1+$A5)^5+'DCF Inputs'!$B$26)/'DCF Inputs'!$B$25 | D5: =('DCF'!$B$5/(1+$A5)^1+'DCF'!$C$5/(1+$A5)^2+'DCF'!$D$5/(1+$A5)^3+'DCF'!$E$5/(1+$A5)^4+'DCF'!$F$5/(1+$A5)^5+('DCF'!$F$5*(1+D$4)/($A5-D$4))/(1+$A5)^5+'DCF Inputs'!$B$26)/'DCF Inputs'!$B$25 | E5: =('DCF'!$B$5/(1+$A5)^1+'DCF'!$C$5/(1+$A5)^2+'DCF'!$D$5/(1+$A5)^3+'DCF'!$E$5/(1+$A5)^4+'DCF'!$F$5/(1+$A5)^5+('DCF'!$F$5*(1+E$4)/($A5-E$4))/(1+$A5)^5+'DCF Inputs'!$B$26)/'DCF Inputs'!$B$25 | F5: =('DCF'!$B$5/(1+$A5)^1+'DCF'!$C$5/(1+$A5)^2+'DCF'!$D$5/(1+$A5)^3+'DCF'!$E$5/(1+$A5)^4+'DCF'!$F$5/(1+$A5)^5+('DCF'!$F$5*(1+F$4)/($A5-F$4))/(1+$A5)^5+'DCF Inputs'!$B$26)/'DCF Inputs'!$B$25
A6: 0.09 | B6: =('DCF'!$B$5/(1+$A6)^1+'DCF'!$C$5/(1+$A6)^2+'DCF'!$D$5/(1+$A6)^3+'DCF'!$E$5/(1+$A6)^4+'DCF'!$F$5/(1+$A6)^5+('DCF'!$F$5*(1+B$4)/($A6-B$4))/(1+$A6)^5+'DCF Inputs'!$B$26)/'DCF Inputs'!$B$25 | C6: =('DCF'!$B$5/(1+$A6)^1+'DCF'!$C$5/(1+$A6)^2+'DCF'!$D$5/(1+$A6)^3+'DCF'!$E$5/(1+$A6)^4+'DCF'!$F$5/(1+$A6)^5+('DCF'!$F$5*(1+C$4)/($A6-C$4))/(1+$A6)^5+'DCF Inputs'!$B$26)/'DCF Inputs'!$B$25 | D6: =('DCF'!$B$5/(1+$A6)^1+'DCF'!$C$5/(1+$A6)^2+'DCF'!$D$5/(1+$A6)^3+'DCF'!$E$5/(1+$A6)^4+'DCF'!$F$5/(1+$A6)^5+('DCF'!$F$5*(1+D$4)/($A6-D$4))/(1+$A6)^5+'DCF Inputs'!$B$26)/'DCF Inputs'!$B$25 | E6: =('DCF'!$B$5/(1+$A6)^1+'DCF'!$C$5/(1+$A6)^2+'DCF'!$D$5/(1+$A6)^3+'DCF'!$E$5/(1+$A6)^4+'DCF'!$F$5/(1+$A6)^5+('DCF'!$F$5*(1+E$4)/($A6-E$4))/(1+$A6)^5+'DCF Inputs'!$B$26)/'DCF Inputs'!$B$25 | F6: =('DCF'!$B$5/(1+$A6)^1+'DCF'!$C$5/(1+$A6)^2+'DCF'!$D$5/(1+$A6)^3+'DCF'!$E$5/(1+$A6)^4+'DCF'!$F$5/(1+$A6)^5+('DCF'!$F$5*(1+F$4)/($A6-F$4))/(1+$A6)^5+'DCF Inputs'!$B$26)/'DCF Inputs'!$B$25
A7: 0.095 | B7: =('DCF'!$B$5/(1+$A7)^1+'DCF'!$C$5/(1+$A7)^2+'DCF'!$D$5/(1+$A7)^3+'DCF'!$E$5/(1+$A7)^4+'DCF'!$F$5/(1+$A7)^5+('DCF'!$F$5*(1+B$4)/($A7-B$4))/(1+$A7)^5+'DCF Inputs'!$B$26)/'DCF Inputs'!$B$25 | C7: =('DCF'!$B$5/(1+$A7)^1+'DCF'!$C$5/(1+$A7)^2+'DCF'!$D$5/(1+$A7)^3+'DCF'!$E$5/(1+$A7)^4+'DCF'!$F$5/(1+$A7)^5+('DCF'!$F$5*(1+C$4)/($A7-C$4))/(1+$A7)^5+'DCF Inputs'!$B$26)/'DCF Inputs'!$B$25 | D7: =('DCF'!$B$5/(1+$A7)^1+'DCF'!$C$5/(1+$A7)^2+'DCF'!$D$5/(1+$A7)^3+'DCF'!$E$5/(1+$A7)^4+'DCF'!$F$5/(1+$A7)^5+('DCF'!$F$5*(1+D$4)/($A7-D$4))/(1+$A7)^5+'DCF Inputs'!$B$26)/'DCF Inputs'!$B$25 | E7: =('DCF'!$B$5/(1+$A7)^1+'DCF'!$C$5/(1+$A7)^2+'DCF'!$D$5/(1+$A7)^3+'DCF'!$E$5/(1+$A7)^4+'DCF'!$F$5/(1+$A7)^5+('DCF'!$F$5*(1+E$4)/($A7-E$4))/(1+$A7)^5+'DCF Inputs'!$B$26)/'DCF Inputs'!$B$25 | F7: =('DCF'!$B$5/(1+$A7)^1+'DCF'!$C$5/(1+$A7)^2+'DCF'!$D$5/(1+$A7)^3+'DCF'!$E$5/(1+$A7)^4+'DCF'!$F$5/(1+$A7)^5+('DCF'!$F$5*(1+F$4)/($A7-F$4))/(1+$A7)^5+'DCF Inputs'!$B$26)/'DCF Inputs'!$B$25
A8: 0.1 | B8: =('DCF'!$B$5/(1+$A8)^1+'DCF'!$C$5/(1+$A8)^2+'DCF'!$D$5/(1+$A8)^3+'DCF'!$E$5/(1+$A8)^4+'DCF'!$F$5/(1+$A8)^5+('DCF'!$F$5*(1+B$4)/($A8-B$4))/(1+$A8)^5+'DCF Inputs'!$B$26)/'DCF Inputs'!$B$25 | C8: =('DCF'!$B$5/(1+$A8)^1+'DCF'!$C$5/(1+$A8)^2+'DCF'!$D$5/(1+$A8)^3+'DCF'!$E$5/(1+$A8)^4+'DCF'!$F$5/(1+$A8)^5+('DCF'!$F$5*(1+C$4)/($A8-C$4))/(1+$A8)^5+'DCF Inputs'!$B$26)/'DCF Inputs'!$B$25 | D8: =('DCF'!$B$5/(1+$A8)^1+'DCF'!$C$5/(1+$A8)^2+'DCF'!$D$5/(1+$A8)^3+'DCF'!$E$5/(1+$A8)^4+'DCF'!$F$5/(1+$A8)^5+('DCF'!$F$5*(1+D$4)/($A8-D$4))/(1+$A8)^5+'DCF Inputs'!$B$26)/'DCF Inputs'!$B$25 | E8: =('DCF'!$B$5/(1+$A8)^1+'DCF'!$C$5/(1+$A8)^2+'DCF'!$D$5/(1+$A8)^3+'DCF'!$E$5/(1+$A8)^4+'DCF'!$F$5/(1+$A8)^5+('DCF'!$F$5*(1+E$4)/($A8-E$4))/(1+$A8)^5+'DCF Inputs'!$B$26)/'DCF Inputs'!$B$25 | F8: =('DCF'!$B$5/(1+$A8)^1+'DCF'!$C$5/(1+$A8)^2+'DCF'!$D$5/(1+$A8)^3+'DCF'!$E$5/(1+$A8)^4+'DCF'!$F$5/(1+$A8)^5+('DCF'!$F$5*(1+F$4)/($A8-F$4))/(1+$A8)^5+'DCF Inputs'!$B$26)/'DCF Inputs'!$B$25
A9: 0.105 | B9: =('DCF'!$B$5/(1+$A9)^1+'DCF'!$C$5/(1+$A9)^2+'DCF'!$D$5/(1+$A9)^3+'DCF'!$E$5/(1+$A9)^4+'DCF'!$F$5/(1+$A9)^5+('DCF'!$F$5*(1+B$4)/($A9-B$4))/(1+$A9)^5+'DCF Inputs'!$B$26)/'DCF Inputs'!$B$25 | C9: =('DCF'!$B$5/(1+$A9)^1+'DCF'!$C$5/(1+$A9)^2+'DCF'!$D$5/(1+$A9)^3+'DCF'!$E$5/(1+$A9)^4+'DCF'!$F$5/(1+$A9)^5+('DCF'!$F$5*(1+C$4)/($A9-C$4))/(1+$A9)^5+'DCF Inputs'!$B$26)/'DCF Inputs'!$B$25 | D9: =('DCF'!$B$5/(1+$A9)^1+'DCF'!$C$5/(1+$A9)^2+'DCF'!$D$5/(1+$A9)^3+'DCF'!$E$5/(1+$A9)^4+'DCF'!$F$5/(1+$A9)^5+('DCF'!$F$5*(1+D$4)/($A9-D$4))/(1+$A9)^5+'DCF Inputs'!$B$26)/'DCF Inputs'!$B$25 | E9: =('DCF'!$B$5/(1+$A9)^1+'DCF'!$C$5/(1+$A9)^2+'DCF'!$D$5/(1+$A9)^3+'DCF'!$E$5/(1+$A9)^4+'DCF'!$F$5/(1+$A9)^5+('DCF'!$F$5*(1+E$4)/($A9-E$4))/(1+$A9)^5+'DCF Inputs'!$B$26)/'DCF Inputs'!$B$25 | F9: =('DCF'!$B$5/(1+$A9)^1+'DCF'!$C$5/(1+$A9)^2+'DCF'!$D$5/(1+$A9)^3+'DCF'!$E$5/(1+$A9)^4+'DCF'!$F$5/(1+$A9)^5+('DCF'!$F$5*(1+F$4)/($A9-F$4))/(1+$A9)^5+'DCF Inputs'!$B$26)/'DCF Inputs'!$B$25
A10: 0.10889 | B10: =('DCF'!$B$5/(1+$A10)^1+'DCF'!$C$5/(1+$A10)^2+'DCF'!$D$5/(1+$A10)^3+'DCF'!$E$5/(1+$A10)^4+'DCF'!$F$5/(1+$A10)^5+('DCF'!$F$5*(1+B$4)/($A10-B$4))/(1+$A10)^5+'DCF Inputs'!$B$26)/'DCF Inputs'!$B$25 | C10: =('DCF'!$B$5/(1+$A10)^1+'DCF'!$C$5/(1+$A10)^2+'DCF'!$D$5/(1+$A10)^3+'DCF'!$E$5/(1+$A10)^4+'DCF'!$F$5/(1+$A10)^5+('DCF'!$F$5*(1+C$4)/($A10-C$4))/(1+$A10)^5+'DCF Inputs'!$B$26)/'DCF Inputs'!$B$25 | D10: =('DCF'!$B$5/(1+$A10)^1+'DCF'!$C$5/(1+$A10)^2+'DCF'!$D$5/(1+$A10)^3+'DCF'!$E$5/(1+$A10)^4+'DCF'!$F$5/(1+$A10)^5+('DCF'!$F$5*(1+D$4)/($A10-D$4))/(1+$A10)^5+'DCF Inputs'!$B$26)/'DCF Inputs'!$B$25 | E10: =('DCF'!$B$5/(1+$A10)^1+'DCF'!$C$5/(1+$A10)^2+'DCF'!$D$5/(1+$A10)^3+'DCF'!$E$5/(1+$A10)^4+'DCF'!$F$5/(1+$A10)^5+('DCF'!$F$5*(1+E$4)/($A10-E$4))/(1+$A10)^5+'DCF Inputs'!$B$26)/'DCF Inputs'!$B$25 | F10: =('DCF'!$B$5/(1+$A10)^1+'DCF'!$C$5/(1+$A10)^2+'DCF'!$D$5/(1+$A10)^3+'DCF'!$E$5/(1+$A10)^4+'DCF'!$F$5/(1+$A10)^5+('DCF'!$F$5*(1+F$4)/($A10-F$4))/(1+$A10)^5+'DCF Inputs'!$B$26)/'DCF Inputs'!$B$25
A11: 0.115 | B11: =('DCF'!$B$5/(1+$A11)^1+'DCF'!$C$5/(1+$A11)^2+'DCF'!$D$5/(1+$A11)^3+'DCF'!$E$5/(1+$A11)^4+'DCF'!$F$5/(1+$A11)^5+('DCF'!$F$5*(1+B$4)/($A11-B$4))/(1+$A11)^5+'DCF Inputs'!$B$26)/'DCF Inputs'!$B$25 | C11: =('DCF'!$B$5/(1+$A11)^1+'DCF'!$C$5/(1+$A11)^2+'DCF'!$D$5/(1+$A11)^3+'DCF'!$E$5/(1+$A11)^4+'DCF'!$F$5/(1+$A11)^5+('DCF'!$F$5*(1+C$4)/($A11-C$4))/(1+$A11)^5+'DCF Inputs'!$B$26)/'DCF Inputs'!$B$25 | D11: =('DCF'!$B$5/(1+$A11)^1+'DCF'!$C$5/(1+$A11)^2+'DCF'!$D$5/(1+$A11)^3+'DCF'!$E$5/(1+$A11)^4+'DCF'!$F$5/(1+$A11)^5+('DCF'!$F$5*(1+D$4)/($A11-D$4))/(1+$A11)^5+'DCF Inputs'!$B$26)/'DCF Inputs'!$B$25 | E11: =('DCF'!$B$5/(1+$A11)^1+'DCF'!$C$5/(1+$A11)^2+'DCF'!$D$5/(1+$A11)^3+'DCF'!$E$5/(1+$A11)^4+'DCF'!$F$5/(1+$A11)^5+('DCF'!$F$5*(1+E$4)/($A11-E$4))/(1+$A11)^5+'DCF Inputs'!$B$26)/'DCF Inputs'!$B$25 | F11: =('DCF'!$B$5/(1+$A11)^1+'DCF'!$C$5/(1+$A11)^2+'DCF'!$D$5/(1+$A11)^3+'DCF'!$E$5/(1+$A11)^4+'DCF'!$F$5/(1+$A11)^5+('DCF'!$F$5*(1+F$4)/($A11-F$4))/(1+$A11)^5+'DCF Inputs'!$B$26)/'DCF Inputs'!$B$25
A12: 0.12 | B12: =('DCF'!$B$5/(1+$A12)^1+'DCF'!$C$5/(1+$A12)^2+'DCF'!$D$5/(1+$A12)^3+'DCF'!$E$5/(1+$A12)^4+'DCF'!$F$5/(1+$A12)^5+('DCF'!$F$5*(1+B$4)/($A12-B$4))/(1+$A12)^5+'DCF Inputs'!$B$26)/'DCF Inputs'!$B$25 | C12: =('DCF'!$B$5/(1+$A12)^1+'DCF'!$C$5/(1+$A12)^2+'DCF'!$D$5/(1+$A12)^3+'DCF'!$E$5/(1+$A12)^4+'DCF'!$F$5/(1+$A12)^5+('DCF'!$F$5*(1+C$4)/($A12-C$4))/(1+$A12)^5+'DCF Inputs'!$B$26)/'DCF Inputs'!$B$25 | D12: =('DCF'!$B$5/(1+$A12)^1+'DCF'!$C$5/(1+$A12)^2+'DCF'!$D$5/(1+$A12)^3+'DCF'!$E$5/(1+$A12)^4+'DCF'!$F$5/(1+$A12)^5+('DCF'!$F$5*(1+D$4)/($A12-D$4))/(1+$A12)^5+'DCF Inputs'!$B$26)/'DCF Inputs'!$B$25 | E12: =('DCF'!$B$5/(1+$A12)^1+'DCF'!$C$5/(1+$A12)^2+'DCF'!$D$5/(1+$A12)^3+'DCF'!$E$5/(1+$A12)^4+'DCF'!$F$5/(1+$A12)^5+('DCF'!$F$5*(1+E$4)/($A12-E$4))/(1+$A12)^5+'DCF Inputs'!$B$26)/'DCF Inputs'!$B$25 | F12: =('DCF'!$B$5/(1+$A12)^1+'DCF'!$C$5/(1+$A12)^2+'DCF'!$D$5/(1+$A12)^3+'DCF'!$E$5/(1+$A12)^4+'DCF'!$F$5/(1+$A12)^5+('DCF'!$F$5*(1+F$4)/($A12-F$4))/(1+$A12)^5+'DCF Inputs'!$B$26)/'DCF Inputs'!$B$25
A14: Shaded = base case (WACC 10.9%, g 3.5%). NVDA is justified near current price only at WACC ≲ 9%.

Sheet Comps
A1: NVIDIA — Comps
A2: Comparable companies — trading multiples; NVDA applied to peer NTM multiples
A4: Company | B4: Ticker | C4: Mkt Cap($B) | D4: EV($B) | E4: EV/Rev LTM | F4: EV/Rev NTM | G4: EV/EBITDA LTM | H4: EV/EBITDA NTM | I4: P/E NTM | J4: Rev Gr% | K4: EBITDA Mgn%
A5: Advanced Micro Devices | B5: AMD | C5: 816.83 | D5: 808.35 | E5: 21.58 | F5: 15.99 | G5: 108.8 | H5: 66.64 | I5: 56.67 | J5: 0.35 | K5: 0.1984
A6: Broadcom | B6: AVGO | C6: 1780 | D6: 1825.28 | E6: 24.19 | F6: 18.6 | G6: 43.38 | H6: 32.08 | I6: 23.76 | J6: 0.3 | K6: 0.5577
A7: Taiwan Semiconductor | B7: TSM | C7: 1980 | D7: 1908.42 | E7: 14.87 | F7: 11.62 | G7: 21.37 | H7: 16.6 | I7: 20.01 | J7: 0.28 | K7: 0.6959
A8: Qualcomm | B8: QCOM | C8: 179.82 | D8: 185.29 | E8: 4.16 | F8: 3.93 | G8: 14.25 | H8: 13.1 | I8: 17.27 | J8: 0.06 | K8: 0.2922
A9: Marvell Technology | B9: MRVL | C9: 164.91 | D9: 166.35 | E9: 19.08 | F9: 13.83 | G9: 61.38 | H9: 38.42 | I9: 41.47 | J9: 0.38 | K9: 0.3111
A10: Micron Technology | B10: MU | C10: 963.6 | D10: 943.96 | E10: 10.46 | F10: 7.75 | G10: 13.84 | H10: 10.19 | I10: 5.95 | J10: 0.35 | K10: 0.7557
A11: Intel | B11: INTC | C11: 487.42 | D11: 499.66 | E11: 9.29 | F11: 8.3 | G11: 35.26 | H11: 30.73 | I11: 89.51 | J11: 0.12 | K11: 0.2636
A12: Arm Holdings | B12: ARM | C12: 279.85 | D12: 276.74 | E12: 56.25 | F12: 43.93 | G12: 261.08 | H12: 183.27 | I12: 120.85 | J12: 0.28 | K12: 0.2164
A14: Maximum | E14: 56.25 | F14: 43.93 | G14: 261.08 | H14: 183.27 | I14: 120.85 | J14: 0.38 | K14: 0.7557
A15: 75th percentile | E15: 23.5375 | F15: 17.9475 | G15: 96.945 | H15: 59.585 | I15: 81.3 | J15: 0.35 | K15: 0.6614
A16: Median | E16: 16.975 | F16: 12.725 | G16: 39.32 | H16: 31.405 | I16: 32.615 | J16: 0.29 | K16: 0.3016
A17: 25th percentile | E17: 9.5825 | F17: 7.8875 | G17: 16.03 | H17: 13.975 | I17: 17.955 | J17: 0.16 | K17: 0.2282
A18: Minimum | E18: 4.16 | F18: 3.93 | G18: 13.84 | H18: 10.19 | I18: 5.95 | J18: 0.06 | K18: 0.1984
A21: APPLIED TO NVDA (NTM = FY2027E)
A22: NVDA NTM EBITDA ($M) | B22: ='Income Statement'!F22
A23: NVDA NTM EPS ($) | B23: ='Income Statement'!F33
A24: NVDA net cash ($M) | B24: ='DCF Inputs'!B26
A25: NVDA shares (M) | B25: ='DCF Inputs'!B25
A26: Implied $/sh — EV/EBITDA (25/med/75) | B26: =(B22*H17+B24)/B25 | C26: =(B22*H16+B24)/B25 | D26: =(B22*H15+B24)/B25
A27: Implied $/sh — P/E (25/med/75) | B27: =B23*I17 | C27: =B23*I16 | D27: =B23*I15
A29: Peers as of 2026-07-17. LTM/NTM per source; NTM applied to NVDA FY2027E.

Sheet Valuation Summary
A1: NVIDIA — Valuation Summary
A2: Football field + weighted price target
A4: Method | B4: Low | C4: Base | D4: High | E4: Weight
A5: DCF (WACC 9.5-12%, g 3-4%) | B5: 129.41 | C5: 156.6 | D5: 209.28 | E5: 0.55
A6: Comps (EV/EBITDA & P/E, NTM) | B6: 131.07 | C6: 270.65 | D6: 621.95 | E6: 0.45
A8: Weighted price target | C8: 207.92
A9: Current price | C9: 207.4
A10: Upside / (downside) | C10: 0.0025
A11: Rating | C11: HOLD
A13: Scenario EPS (FY2031E): Bear $7.9 / Base $15.7 / Bull $22+ (see Scenarios tab).
A14: Weighting: DCF 55% (transparent 5-yr forecast), Comps 45%. Precedent transactions N/A for a ~$5T name.
